county_adjacency/__init__.py
county_adjacency/adjacency.py
county_adjacency/data.py
county_adjacency/data2.py
county_adjacency/errors.py
county_adjacency-0.1.3.dist-info/LICENSE
county_adjacency-0.1.3.dist-info/METADATA
county_adjacency-0.1.3.dist-info/WHEEL
county_adjacency-0.1.3.dist-info/top_level.txt
county_adjacency-0.1.3.dist-info/RECORD
