Metadata-Version: 2.1
Name: county-adjacency
Version: 0.1.3
Summary: This package provides adjacency information for US counties (or their equivalent).
Home-page: https://github.com/chaddotson/county_adjacency
Author: Chad Dotson
License: MIT
Project-URL: Source, https://github.com/chaddotson/county_adjacency
Project-URL: Tracker, https://github.com/chaddotson/county_adjacency/issues
Keywords: geography,geo,counties,us
Platform: unix
Platform: linux
Platform: osx
Platform: cygwin
Platform: win32
Classifier: Development Status :: 3 - Alpha
Classifier: Intended Audience :: Developers
Classifier: License :: OSI Approved :: MIT License
Classifier: Operating System :: MacOS :: MacOS X
Classifier: Operating System :: Microsoft :: Windows
Classifier: Operating System :: POSIX
Classifier: Programming Language :: Python :: 3
Classifier: Programming Language :: Python :: 3 :: Only
Classifier: Programming Language :: Python :: 3.6
Classifier: Programming Language :: Python :: 3.7
Classifier: Programming Language :: Python :: 3.8
Classifier: Programming Language :: Python :: 3.9
Classifier: Topic :: Education
Classifier: Topic :: Scientific/Engineering
Classifier: Topic :: Scientific/Engineering :: GIS
Classifier: Topic :: Utilities
Requires-Python: >=3.6
Requires-Dist: python-Levenshtein (==0.12.0)
Provides-Extra: dev
Requires-Dist: black (==20.8b1) ; extra == 'dev'
Requires-Dist: coverage (>=5.0) ; extra == 'dev'
Requires-Dist: flake8 (>=3.8.0) ; extra == 'dev'
Requires-Dist: flake8-docstrings (>=1.5.0) ; extra == 'dev'
Requires-Dist: flake8-rst-docstrings (>=0.0.14) ; extra == 'dev'
Requires-Dist: requests (==2.25.0) ; extra == 'dev'
Requires-Dist: pytest (>=6.1) ; extra == 'dev'
